RTL/systolic_array/Multiplier/Bam_cell.v
module Bam_cell(
	input	wire	A,
	input	wire	B,
	input	wire	pre_OUT,
	input	wire	Carry,

	output	wire	Carry_out,
	output	wire	OUT
);

  	wire			and_ab;
	wire	[1:0]	result;

	assign	and_ab 		= A & B;
	assign	result		= and_ab + pre_OUT + Carry;	

	assign	Carry_out	= result[1];
	assign	OUT		= result[0];
	
endmodule

TB/Multiplier_tb/tb_bam_cell.sv
module tb_bam_cell;
  
  logic A, B, pre_OUT, Carry, Carry_out, OUT;
  
  Bam_cell dut(
    .A(A),
    .B(B),
    .pre_OUT(pre_OUT),
    .Carry(Carry),
    .Carry_out(Carry_out),
    .OUT(OUT)
  );
  
  initial begin
    $dumpfile("bam_cell.vcd");
  	$dumpvars(0, tb_bam_cell);
    
    for(int i=0; i<2; i++) begin
      for(int j=0; j<2; j++) begin
        for(int k=0; k<2; k++) begin
          for(int l=0; l<2; l++) begin
        	A=i;B=j;Carry=k;pre_OUT=l;
        	#1;
        	$display("\n===== A=%b B=%b pre_OUT=%b Carry=%b | AND=%b SUM=%0d | OUT=%b COUT=%b =====", A, B, pre_OUT, Carry, (A & B), (A & B) + pre_OUT + Carry, OUT, Carry_out);
          end
        end
      end
    end
    
    #1 $finish;
  end
  
endmodule

TB/Multiplier_tb/bam_cell.vcd
$date
	Mon Mar  9 15:02:45 2026
$end
$version
	QuestaSim Version 2021.2_1
$end
$timescale
	1ns
$end

$scope module tb_bam_cell $end
$var reg 1 ! A $end
$var reg 1 " B $end
$var reg 1 # pre_OUT $end
$var reg 1 $ Carry $end
$var reg 1 % Carry_out $end
$var reg 1 & OUT $end

$scope module dut $end
$var wire 1 ' A $end
$var wire 1 ( B $end
$var wire 1 ) pre_OUT $end
$var wire 1 * Carry $end
$var wire 1 + Carry_out $end
$var wire 1 , OUT $end
$var wire 1 - and_ab $end
$var wire 1 . result [1] $end
$var wire 1 / result [0] $end
$upscope $end
$upscope $end
$enddefinitions $end
#0
$dumpvars
0!
0"
0#
0$
0%
0&
0-
0/
0.
0*
0)
0(
0'
0+
0,
$end
#1
1#
1)
1/
1,
1&
#2
1$
0#
1*
0)
#3
1#
1)
0/
1.
1+
0,
0&
1%
#4
1"
0$
0#
1(
0*
0)
0.
0+
0%
#5
1#
1)
1/
1,
1&
#6
1$
0#
1*
0)
#7
1#
1)
0/
1.
1+
0,
0&
1%
#8
1!
0"
0$
0#
1'
0(
0*
0)
0.
0+
0%
#9
1#
1)
1/
1,
1&
#10
1$
0#
1*
0)
#11
1#
1)
0/
1.
1+
0,
0&
1%
#12
1"
0$
0#
1(
0*
0)
1-
1/
0.
0+
1,
1&
0%
#13
1#
1)
0/
1.
1+
0,
0&
1%
#14
1$
0#
1*
0)
#15
1#
1)
1/
1,
1&
