RTL/systolic_array/Multiplier/lopd.v
module lopd #(
    parameter WIDTH_I = 16,
    parameter WIDTH_L = clog2(WIDTH_I)
)(
    input  wire [WIDTH_I-1:0] in,
    output reg  [WIDTH_L-1:0] out
);

    function automatic integer clog2;
        input integer value;
        integer i;
        begin
            clog2 = 0;
            for (i = value - 1; i > 0; i = i >> 1)
                clog2 = clog2 + 1;
        end
    endfunction

    integer i;

    always @(*) begin
        out = {WIDTH_L{1'b0}};
        for (i = 0; i < WIDTH_I; i = i + 1) begin
            if (in[i])
                out = i;
        end
    end

endmodule

TB/Multiplier_tb/tp_lopd.sv
`timescale 1ns/1ps

module tb_lopd;

    localparam WIDTH_I = 16;
    localparam WIDTH_L = $clog2(WIDTH_I);

    reg  [WIDTH_I-1:0] in;
    wire [WIDTH_L-1:0] out;

    lopd #(
        .WIDTH_I(WIDTH_I),
        .WIDTH_L(WIDTH_L)
    ) dut (
        .in(in),
        .out(out)
    );

    task check;
        input [WIDTH_I-1:0] value;
        integer i;
        reg [WIDTH_L-1:0] golden;
    begin
        in = value;
        #1;

        golden = 0;
        for (i = 0; i < WIDTH_I; i = i + 1)
            if (value[i])
                golden = i;

        $display("\n===== IN = %b | OUT = %0d | GOLD = %0d ===== \n%s",
                 in, out, golden,
                 (out === golden) ? "PASSED" : "FAILED");

        if (out !== golden)
            $stop;
    end
    endtask

    initial begin
        $dumpfile("tb_lopd.vcd");
        $dumpvars(0, tb_lopd);

        check(16'b0000_0000_0000_0001);
        check(16'b0000_0000_0000_1000);
        check(16'b0000_0001_0100_0000);
        check(16'b1000_0000_0000_0000);

        check(16'b0000_0000_1111_0000);
        check(16'b0101_0101_0101_0101);

        check(16'b0);

        repeat (20)
            check($random);

        $display("=== ALL TEST PASSED ===");
        $finish;
    end

endmodule

TB/Multiplier_tb/tb_lopd.vcd
$date
	Mon Mar  9 15:36:33 2026
$end
$version
	QuestaSim Version 2021.2_1
$end
$timescale
	1ps
$end

$scope module tb_lopd $end
$var parameter 32 ! WIDTH_I $end
$var parameter 32 " WIDTH_L $end
$var reg 16 # in [15:0] $end
$var wire 1 $ out [3] $end
$var wire 1 % out [2] $end
$var wire 1 & out [1] $end
$var wire 1 ' out [0] $end

$scope task check $end
$var reg 16 ( value [15:0] $end
$var integer 32 ) i $end
$var reg 4 * golden [3:0] $end
$upscope $end

$scope module dut $end
$var parameter 32 + WIDTH_I $end
$var parameter 32 , WIDTH_L $end
$var wire 1 - in [15] $end
$var wire 1 . in [14] $end
$var wire 1 / in [13] $end
$var wire 1 0 in [12] $end
$var wire 1 1 in [11] $end
$var wire 1 2 in [10] $end
$var wire 1 3 in [9] $end
$var wire 1 4 in [8] $end
$var wire 1 5 in [7] $end
$var wire 1 6 in [6] $end
$var wire 1 7 in [5] $end
$var wire 1 8 in [4] $end
$var wire 1 9 in [3] $end
$var wire 1 : in [2] $end
$var wire 1 ; in [1] $end
$var wire 1 < in [0] $end
$var reg 4 = out [3:0] $end
$var integer 32 > i $end

$scope function clog2 $end
$upscope $end
$upscope $end
$upscope $end
$enddefinitions $end
#0
$dumpvars
b1 #
b0 =
b1 (
bx *
b10000 !
b100 "
b10000 +
b100 ,
b10000 >
bx )
0'
0&
0%
0$
1<
0;
0:
09
08
07
06
05
04
03
02
01
00
0/
0.
0-
$end
#1000
b0 *
b0 )
b1 )
b10 )
b11 )
b100 )
b101 )
b110 )
b111 )
b1000 )
b1001 )
b1010 )
b1011 )
b1100 )
b1101 )
b1110 )
b1111 )
b10000 )
b1000 (
b1000 #
0<
19
b0 >
b1 >
b10 >
b11 >
b11 =
b100 >
b101 >
b110 >
b111 >
b1000 >
b1001 >
b1010 >
b1011 >
b1100 >
b1101 >
b1110 >
b1111 >
b10000 >
1'
1&
#2000
b0 )
b1 )
b10 )
b11 )
b11 *
b100 )
b101 )
b110 )
b111 )
b1000 )
b1001 )
b1010 )
b1011 )
b1100 )
b1101 )
b1110 )
b1111 )
b10000 )
b101000000 (
b101000000 #
09
16
14
b0 =
b0 >
b1 >
b10 >
b11 >
b100 >
b101 >
b110 >
b110 =
b111 >
b1000 >
b1000 =
b1001 >
b1010 >
b1011 >
b1100 >
b1101 >
b1110 >
b1111 >
b10000 >
0'
0&
1$
#3000
b0 *
b0 )
b1 )
b10 )
b11 )
b100 )
b101 )
b110 )
b110 *
b111 )
b1000 )
b1000 *
b1001 )
b1010 )
b1011 )
b1100 )
b1101 )
b1110 )
b1111 )
b10000 )
b1000000000000000 (
b1000000000000000 #
06
04
1-
b0 =
b0 >
b1 >
b10 >
b11 >
b100 >
b101 >
b110 >
b111 >
b1000 >
b1001 >
b1010 >
b1011 >
b1100 >
b1101 >
b1110 >
b1111 >
b1111 =
b10000 >
1'
1&
1%
#4000
b0 *
b0 )
b1 )
b10 )
b11 )
b100 )
b101 )
b110 )
b111 )
b1000 )
b1001 )
b1010 )
b1011 )
b1100 )
b1101 )
b1110 )
b1111 )
b1111 *
b10000 )
b11110000 (
b11110000 #
18
17
16
15
0-
b0 =
b0 >
b1 >
b10 >
b11 >
b100 >
b100 =
b101 >
b101 =
b110 >
b110 =
b111 >
b111 =
b1000 >
b1001 >
b1010 >
b1011 >
b1100 >
b1101 >
b1110 >
b1111 >
b10000 >
0$
#5000
b0 *
b0 )
b1 )
b10 )
b11 )
b100 )
b100 *
b101 )
b101 *
b110 )
b110 *
b111 )
b111 *
b1000 )
b1001 )
b1010 )
b1011 )
b1100 )
b1101 )
b1110 )
b1111 )
b10000 )
b101010101010101 (
b101010101010101 #
1<
1:
07
05
14
12
10
1.
b0 =
b0 >
b1 >
b10 >
b10 =
b11 >
b100 >
b100 =
b101 >
b110 >
b110 =
b111 >
b1000 >
b1000 =
b1001 >
b1010 >
b1010 =
b1011 >
b1100 >
b1100 =
b1101 >
b1110 >
b1110 =
b1111 >
b10000 >
0'
1$
#6000
b0 *
b0 )
b1 )
b10 )
b10 *
b11 )
b100 )
b100 *
b101 )
b110 )
b110 *
b111 )
b1000 )
b1000 *
b1001 )
b1010 )
b1010 *
b1011 )
b1100 )
b1100 *
b1101 )
b1110 )
b1110 *
b1111 )
b10000 )
b0 (
b0 #
0<
0:
08
06
04
02
00
0.
b0 =
b0 >
b1 >
b10 >
b11 >
b100 >
b101 >
b110 >
b111 >
b1000 >
b1001 >
b1010 >
b1011 >
b1100 >
b1101 >
b1110 >
b1111 >
b10000 >
0&
0%
0$
#7000
b0 *
b0 )
b1 )
b10 )
b11 )
b100 )
b101 )
b110 )
b111 )
b1000 )
b1001 )
b1010 )
b1011 )
b1100 )
b1101 )
b1110 )
b1111 )
b10000 )
b11010100100100 (
b11010100100100 #
1:
17
14
12
10
1/
b0 >
b1 >
b10 >
b10 =
b11 >
b100 >
b101 >
b101 =
b110 >
b111 >
b1000 >
b1000 =
b1001 >
b1010 >
b1010 =
b1011 >
b1100 >
b1100 =
b1101 >
b1101 =
b1110 >
b1111 >
b10000 >
1'
1%
1$
#8000
b0 )
b1 )
b10 )
b10 *
b11 )
b100 )
b101 )
b101 *
b110 )
b111 )
b1000 )
b1000 *
b1001 )
b1010 )
b1010 *
b1011 )
b1100 )
b1100 *
b1101 )
b1101 *
b1110 )
b1111 )
b10000 )
b101111010000001 (
b101111010000001 #
1<
0:
07
15
04
13
11
0/
1.
b0 =
b0 >
b1 >
b10 >
b11 >
b100 >
b101 >
b110 >
b111 >
b111 =
b1000 >
b1001 >
b1001 =
b1010 >
b1010 =
b1011 >
b1011 =
b1100 >
b1100 =
b1101 >
b1110 >
b1110 =
b1111 >
b10000 >
0'
1&
#9000
b0 *
b0 )
b1 )
b10 )
b11 )
b100 )
b101 )
b110 )
b111 )
b111 *
b1000 )
b1001 )
b1001 *
b1010 )
b1010 *
b1011 )
b1011 *
b1100 )
b1100 *
b1101 )
b1110 )
b1110 *
b1111 )
b10000 )
b1101011000001001 (
b1101011000001001 #
19
05
01
1-
b0 =
b0 >
b1 >
b10 >
b11 >
b11 =
b100 >
b101 >
b110 >
b111 >
b1000 >
b1001 >
b1001 =
b1010 >
b1010 =
b1011 >
b1100 >
b1100 =
b1101 >
b1110 >
b1110 =
b1111 >
b1111 =
b10000 >
1'
#10000
b0 *
b0 )
b1 )
b10 )
b11 )
b11 *
b100 )
b101 )
b110 )
b111 )
b1000 )
b1001 )
b1001 *
b1010 )
b1010 *
b1011 )
b1100 )
b1100 *
b1101 )
b1110 )
b1110 *
b1111 )
b1111 *
b10000 )
b101011001100011 (
b101011001100011 #
1;
09
17
16
0-
b0 =
b0 >
b1 >
b1 =
b10 >
b11 >
b100 >
b101 >
b101 =
b110 >
b110 =
b111 >
b1000 >
b1001 >
b1001 =
b1010 >
b1010 =
b1011 >
b1100 >
b1100 =
b1101 >
b1110 >
b1110 =
b1111 >
b10000 >
0'
#11000
b0 *
b0 )
b1 )
b1 *
b10 )
b11 )
b100 )
b101 )
b101 *
b110 )
b110 *
b111 )
b1000 )
b1001 )
b1001 *
b1010 )
b1010 *
b1011 )
b1100 )
b1100 *
b1101 )
b1110 )
b1110 *
b1111 )
b10000 )
b111101100001101 (
b111101100001101 #
0;
1:
19
07
06
14
02
11
1/
b0 =
b0 >
b1 >
b10 >
b10 =
b11 >
b11 =
b100 >
b101 >
b110 >
b111 >
b1000 >
b1000 =
b1001 >
b1001 =
b1010 >
b1011 >
b1011 =
b1100 >
b1100 =
b1101 >
b1101 =
b1110 >
b1110 =
b1111 >
b10000 >
#12000
b0 *
b0 )
b1 )
b10 )
b10 *
b11 )
b11 *
b100 )
b101 )
b110 )
b111 )
b1000 )
b1000 *
b1001 )
b1001 *
b1010 )
b1011 )
b1011 *
b1100 )
b1100 *
b1101 )
b1101 *
b1110 )
b1110 *
b1111 )
b10000 )
b1001100110001101 (
b1001100110001101 #
15
03
0/
0.
1-
b0 =
b0 >
b1 >
b10 >
b10 =
b11 >
b11 =
b100 >
b101 >
b110 >
b111 >
b111 =
b1000 >
b1000 =
b1001 >
b1010 >
b1011 >
b1011 =
b1100 >
b1100 =
b1101 >
b1110 >
b1111 >
b1111 =
b10000 >
1'
#13000
b0 *
b0 )
b1 )
b10 )
b10 *
b11 )
b11 *
b100 )
b101 )
b110 )
b111 )
b111 *
b1000 )
b1000 *
b1001 )
b1010 )
b1011 )
b1011 *
b1100 )
b1100 *
b1101 )
b1110 )
b1111 )
b1111 *
b10000 )
b1000010001100101 (
b1000010001100101 #
09
17
16
05
04
12
01
00
b0 =
b0 >
b1 >
b10 >
b10 =
b11 >
b100 >
b101 >
b101 =
b110 >
b110 =
b111 >
b1000 >
b1001 >
b1010 >
b1010 =
b1011 >
b1100 >
b1101 >
b1110 >
b1111 >
b1111 =
b10000 >
#14000
b0 *
b0 )
b1 )
b10 )
b10 *
b11 )
b100 )
b101 )
b101 *
b110 )
b110 *
b111 )
b1000 )
b1001 )
b1010 )
b1010 *
b1011 )
b1100 )
b1101 )
b1110 )
b1111 )
b1111 *
b10000 )
b101001000010010 (
b101001000010010 #
0<
1;
0:
18
07
06
13
02
10
1.
0-
b0 =
b0 >
b1 >
b1 =
b10 >
b11 >
b100 >
b100 =
b101 >
b110 >
b111 >
b1000 >
b1001 >
b1001 =
b1010 >
b1011 >
b1100 >
b1100 =
b1101 >
b1110 >
b1110 =
b1111 >
b10000 >
0'
#15000
b0 *
b0 )
b1 )
b1 *
b10 )
b11 )
b100 )
b100 *
b101 )
b110 )
b111 )
b1000 )
b1001 )
b1001 *
b1010 )
b1011 )
b1100 )
b1100 *
b1101 )
b1110 )
b1110 *
b1111 )
b10000 )
b1110001100000001 (
b1110001100000001 #
1<
0;
08
14
00
1/
1-
b0 =
b0 >
b1 >
b10 >
b11 >
b100 >
b101 >
b110 >
b111 >
b1000 >
b1000 =
b1001 >
b1001 =
b1010 >
b1011 >
b1100 >
b1101 >
b1101 =
b1110 >
b1110 =
b1111 >
b1111 =
b10000 >
1'
#16000
b0 *
b0 )
b1 )
b10 )
b11 )
b100 )
b101 )
b110 )
b111 )
b1000 )
b1000 *
b1001 )
b1001 *
b1010 )
b1011 )
b1100 )
b1101 )
b1101 *
b1110 )
b1110 *
b1111 )
b1111 *
b10000 )
b1100110100001101 (
b1100110100001101 #
1:
19
03
12
11
0/
b0 =
b0 >
b1 >
b10 >
b10 =
b11 >
b11 =
b100 >
b101 >
b110 >
b111 >
b1000 >
b1000 =
b1001 >
b1010 >
b1010 =
b1011 >
b1011 =
b1100 >
b1101 >
b1110 >
b1110 =
b1111 >
b1111 =
b10000 >
#17000
b0 *
b0 )
b1 )
b10 )
b10 *
b11 )
b11 *
b100 )
b101 )
b110 )
b111 )
b1000 )
b1000 *
b1001 )
b1010 )
b1010 *
b1011 )
b1011 *
b1100 )
b1101 )
b1110 )
b1110 *
b1111 )
b1111 *
b10000 )
b1111000101110110 (
b1111000101110110 #
0<
1;
09
18
17
16
02
01
10
1/
b0 =
b0 >
b1 >
b1 =
b10 >
b10 =
b11 >
b100 >
b100 =
b101 >
b101 =
b110 >
b110 =
b111 >
b1000 >
b1000 =
b1001 >
b1010 >
b1011 >
b1100 >
b1100 =
b1101 >
b1101 =
b1110 >
b1110 =
b1111 >
b1111 =
b10000 >
#18000
b0 *
b0 )
b1 )
b1 *
b10 )
b10 *
b11 )
b100 )
b100 *
b101 )
b101 *
b110 )
b110 *
b111 )
b1000 )
b1000 *
b1001 )
b1010 )
b1011 )
b1100 )
b1100 *
b1101 )
b1101 *
b1110 )
b1110 *
b1111 )
b1111 *
b10000 )
b1100110100111101 (
b1100110100111101 #
1<
0;
19
06
12
11
00
0/
b0 =
b0 >
b1 >
b10 >
b10 =
b11 >
b11 =
b100 >
b100 =
b101 >
b101 =
b110 >
b111 >
b1000 >
b1000 =
b1001 >
b1010 >
b1010 =
b1011 >
b1011 =
b1100 >
b1101 >
b1110 >
b1110 =
b1111 >
b1111 =
b10000 >
#19000
b0 *
b0 )
b1 )
b10 )
b10 *
b11 )
b11 *
b100 )
b100 *
b101 )
b101 *
b110 )
b111 )
b1000 )
b1000 *
b1001 )
b1010 )
b1010 *
b1011 )
b1011 *
b1100 )
b1101 )
b1110 )
b1110 *
b1111 )
b1111 *
b10000 )
b101011111101101 (
b101011111101101 #
08
16
15
13
01
10
0-
b0 =
b0 >
b1 >
b10 >
b10 =
b11 >
b11 =
b100 >
b101 >
b101 =
b110 >
b110 =
b111 >
b111 =
b1000 >
b1000 =
b1001 >
b1001 =
b1010 >
b1010 =
b1011 >
b1100 >
b1100 =
b1101 >
b1110 >
b1110 =
b1111 >
b10000 >
0'
#20000
b0 *
b0 )
b1 )
b10 )
b10 *
b11 )
b11 *
b100 )
b101 )
b101 *
b110 )
b110 *
b111 )
b111 *
b1000 )
b1000 *
b1001 )
b1001 *
b1010 )
b1010 *
b1011 )
b1100 )
b1100 *
b1101 )
b1110 )
b1110 *
b1111 )
b10000 )
b1111011110001100 (
b1111011110001100 #
0<
07
06
1/
1-
b0 =
b0 >
b1 >
b10 >
b10 =
b11 >
b11 =
b100 >
b101 >
b110 >
b111 >
b111 =
b1000 >
b1000 =
b1001 >
b1001 =
b1010 >
b1010 =
b1011 >
b1100 >
b1100 =
b1101 >
b1101 =
b1110 >
b1110 =
b1111 >
b1111 =
b10000 >
1'
#21000
b0 *
b0 )
b1 )
b10 )
b10 *
b11 )
b11 *
b100 )
b101 )
b110 )
b111 )
b111 *
b1000 )
b1000 *
b1001 )
b1001 *
b1010 )
b1010 *
b1011 )
b1100 )
b1100 *
b1101 )
b1101 *
b1110 )
b1110 *
b1111 )
b1111 *
b10000 )
b1110100111111001 (
b1110100111111001 #
1<
0:
18
17
16
03
02
11
00
b0 =
b0 >
b1 >
b10 >
b11 >
b11 =
b100 >
b100 =
b101 >
b101 =
b110 >
b110 =
b111 >
b111 =
b1000 >
b1000 =
b1001 >
b1010 >
b1011 >
b1011 =
b1100 >
b1101 >
b1101 =
b1110 >
b1110 =
b1111 >
b1111 =
b10000 >
#22000
b0 *
b0 )
b1 )
b10 )
b11 )
b11 *
b100 )
b100 *
b101 )
b101 *
b110 )
b110 *
b111 )
b111 *
b1000 )
b1000 *
b1001 )
b1010 )
b1011 )
b1011 *
b1100 )
b1101 )
b1101 *
b1110 )
b1110 *
b1111 )
b1111 *
b10000 )
b10010011000110 (
b10010011000110 #
0<
1;
1:
09
08
07
04
12
01
0.
0-
b0 =
b0 >
b1 >
b1 =
b10 >
b10 =
b11 >
b100 >
b101 >
b110 >
b110 =
b111 >
b111 =
b1000 >
b1001 >
b1010 >
b1010 =
b1011 >
b1100 >
b1101 >
b1101 =
b1110 >
b1111 >
b10000 >
0&
#23000
b0 *
b0 )
b1 )
b1 *
b10 )
b10 *
b11 )
b100 )
b101 )
b110 )
b110 *
b111 )
b111 *
b1000 )
b1001 )
b1010 )
b1010 *
b1011 )
b1100 )
b1101 )
b1101 *
b1110 )
b1111 )
b10000 )
b1000010011000101 (
b1000010011000101 #
1<
0;
0/
1-
b0 =
b0 >
b1 >
b10 >
b10 =
b11 >
b100 >
b101 >
b110 >
b110 =
b111 >
b111 =
b1000 >
b1001 >
b1010 >
b1010 =
b1011 >
b1100 >
b1101 >
b1110 >
b1111 >
b1111 =
b10000 >
1&
#24000
b0 *
b0 )
b1 )
b10 )
b10 *
b11 )
b100 )
b101 )
b110 )
b110 *
b111 )
b111 *
b1000 )
b1001 )
b1010 )
b1010 *
b1011 )
b1100 )
b1101 )
b1110 )
b1111 )
b1111 *
b10000 )
b1101001010101010 (
b1101001010101010 #
0<
1;
0:
19
17
06
13
02
10
1.
b0 =
b0 >
b1 >
b1 =
b10 >
b11 >
b11 =
b100 >
b101 >
b101 =
b110 >
b111 >
b111 =
b1000 >
b1001 >
b1001 =
b1010 >
b1011 >
b1100 >
b1100 =
b1101 >
b1110 >
b1110 =
b1111 >
b1111 =
b10000 >
#25000
b0 *
b0 )
b1 )
b1 *
b10 )
b11 )
b11 *
b100 )
b101 )
b101 *
b110 )
b111 )
b111 *
b1000 )
b1001 )
b1001 *
b1010 )
b1011 )
b1100 )
b1100 *
b1101 )
b1110 )
b1110 *
b1111 )
b1111 *
b10000 )
b1111011111100101 (
b1111011111100101 #
1<
0;
1:
09
16
14
12
1/
b0 =
b0 >
b1 >
b10 >
b10 =
b11 >
b100 >
b101 >
b101 =
b110 >
b110 =
b111 >
b111 =
b1000 >
b1000 =
b1001 >
b1001 =
b1010 >
b1010 =
b1011 >
b1100 >
b1100 =
b1101 >
b1101 =
b1110 >
b1110 =
b1111 >
b1111 =
b10000 >
#26000
b0 *
b0 )
b1 )
b10 )
b10 *
b11 )
b100 )
b101 )
b101 *
b110 )
b110 *
b111 )
b111 *
b1000 )
b1000 *
b1001 )
b1001 *
b1010 )
b1010 *
b1011 )
b1100 )
b1100 *
b1101 )
b1101 *
b1110 )
b1110 *
b1111 )
b1111 *
b10000 )
b111001001110111 (
b111001001110111 #
1;
18
05
04
02
0-
b0 =
b0 >
b1 >
b1 =
b10 >
b10 =
b11 >
b100 >
b100 =
b101 >
b101 =
b110 >
b110 =
b111 >
b1000 >
b1001 >
b1001 =
b1010 >
b1011 >
b1100 >
b1100 =
b1101 >
b1101 =
b1110 >
b1110 =
b1111 >
b10000 >
0'
#27000
b0 *
b0 )
b1 )
b1 *
b10 )
b10 *
b11 )
b100 )
b100 *
b101 )
b101 *
b110 )
b110 *
b111 )
b1000 )
b1001 )
b1001 *
b1010 )
b1011 )
b1100 )
b1100 *
b1101 )
b1101 *
b1110 )
b1110 *
b1111 )
b10000 )
