RTL/systolic_array/Multiplier/Multiplier_booth.v
`define max(a,b) ((a) > (b) ? (a) : (b))

module Multiplier_booth #(
	parameter APPROX_TYPE	= 0,
	parameter APPROX_W		= 16,			//Number of bit will approximate
	parameter WIDTH_A 		= 16,
	parameter WIDTH_B 		= 16,
	parameter WIDTH_MUL 	= WIDTH_A + WIDTH_B,
	parameter SIGNED 		= 0,
	parameter STAGE			= 0				//Number of pipeline stage
)(
	input	wire					clk,
	input	wire					rst_n,
	input	wire					pip_en,
	input	wire	[WIDTH_A-1:0]	A,
	input	wire	[WIDTH_B-1:0]	B,

	output	wire	[WIDTH_MUL-1:0]	OUT
);

	//Derived Parameters
	parameter WIDTH = `max(WIDTH_A, WIDTH_B);	
	parameter cnt	= (WIDTH + 1)/2;			//Radix-4 only need n/2

	//Internal Signals
	wire			[2:0]				Q;
	wire	signed	[WIDTH_MUL-1:0]		A_ext;
	wire			[WIDTH_B+2:0]		B_ext;
	wire								done;
	reg									done_reg;
	
	reg 	signed 	[WIDTH_MUL-1:0] 	OUT_final;
	reg		signed	[WIDTH_MUL-1:0]		product;
	reg				[5:0]				i;
	reg 	signed 	[WIDTH_MUL-1:0] 	pipe_reg [0:STAGE];		//Stimulate pipeline
	integer 							p;

	//Take 3 bits from B to calculate and then shift to higher and continue taking bits
	assign 	Q 		= 	B_ext[2*i +: 3];

	//Sign extend if SIGNED = 1
	assign	A_ext 	= SIGNED ? $signed({{WIDTH_B{A[WIDTH_A-1]}} , A}) : $signed({{WIDTH_B{1'b0}}, A});	
	//If SIGNED, add 1 bit 0 to LSB and 2 bit SIGN of B to MSB, if not add 1 bit 0 to LSB and 2 bit 0 to MSB
	assign 	B_ext 	= SIGNED ? {{2{B[WIDTH_B-1]}}, B, 1'b0} : {2'b0, B, 1'b0};	
	assign	done	= done_reg;

	always @(posedge clk or negedge rst_n) begin
		if(!rst_n) begin
			product		<= {WIDTH_MUL{1'b0}};
			i			<= 6'b0;
			done_reg	<= 1'b0;
		end
		else if (pip_en) begin
			if(i == 0) begin
				product		<= {WIDTH_MUL{1'b0}};
			end
			if(i<cnt) begin
				case(Q)
					3'b000: product	<= product;							//Keep product
					3'b001: product	<= product + (A_ext << (2*i));		//product = product + 1 * A
					3'b010: product	<= product + (A_ext << (2*i));		//product = product + 1 * A
					3'b011: product	<= product + (A_ext << (2*i+1));	//product = product + 2 * A
					3'b100: product	<= product - (A_ext << (2*i+1));	//product = product - 2 * A
					3'b101: product	<= product - (A_ext << (2*i));		//product = product - 1 * A
					3'b110: product	<= product - (A_ext << (2*i));		//product = product - 1 * A
					3'b111: product	<= product;							//Keep product
				endcase
				i <= i + 1'b1;		//Increase i to continue loop
				if(i == (cnt -1))	//Finish all counting (0 -> (cnt-1))
					done_reg	<= 1'b1;	//done_reg signal high
				else 
					done_reg	<= 1'b0;
			end
			else begin
				i			<= 6'b0;
				done_reg	<= 1'b0;
			end
		end
	end

	//Stimulate pipeline stage
	always @(posedge clk or negedge rst_n) begin
		if (!rst_n) begin
       		for(p = 0; p <= STAGE; p = p + 1) begin
				pipe_reg[p]		<= {WIDTH_MUL{1'b0}};	//Reset all pipeline stage
			end
		end
		else if (pip_en && done) begin
    		if(APPROX_TYPE)
				//Trans approximate bit to 0 to reduce power
				pipe_reg[0] <= {product[WIDTH_MUL-1:APPROX_W], {APPROX_W{1'b0}}};
			else
				pipe_reg[0]	<= product;

    		for (p = 1; p <= STAGE; p = p + 1) begin
        		pipe_reg[p] <= pipe_reg[p-1];			//Stimulate pipeline stage
			end
		end
	end

	assign OUT = pipe_reg[STAGE];						//OUT result when finish all pipeline stages
endmodule

TB/Multiplier_tb/tb_multiplier_booth.sv
module tb_multiplier_booth;

	parameter 	WIDTH_A   	= 16;
	parameter 	WIDTH_B   	= 16;
	parameter 	WIDTH_MUL 	= WIDTH_A + WIDTH_B;
	parameter 	SIGNED    	= 0;
	parameter 	STAGE     	= 0;
	parameter 	APPROX_TYPE = 0;
	parameter 	APPROX_W    = 0;

	localparam 	WIDTH 	= (WIDTH_A > WIDTH_B) ? WIDTH_A : WIDTH_B;
	localparam 	CNT   	= (WIDTH + 1) / 2;
	localparam 	LATENCY = CNT + STAGE;

	logic clk;
	logic rst_n;
	logic pip_en;

	logic [WIDTH_A-1:0] A;
	logic [WIDTH_B-1:0] B;

	wire  [WIDTH_MUL-1:0] OUT;

	Multiplier_booth #(
		.APPROX_TYPE(APPROX_TYPE),
		.APPROX_W   (APPROX_W),
		.WIDTH_A    (WIDTH_A),
		.WIDTH_B    (WIDTH_B),
		.WIDTH_MUL  (WIDTH_MUL),
		.SIGNED     (SIGNED),
		.STAGE      (STAGE)
	) dut (
		.clk    (clk),
		.rst_n  (rst_n),
		.pip_en (pip_en),
		.A      (A),
		.B      (B),
		.OUT    (OUT)
	);

	always #5 clk = ~clk;


	task run_test(input int a, input int b);
		int exp;
	begin
		A = a;
		B = b;
		pip_en = 1'b1;

		exp = SIGNED ? ($signed(a) * $signed(b)) : (a * b);

		repeat (LATENCY + 1) @(posedge clk);
		#1;

		if (APPROX_TYPE)
			exp = (exp >> APPROX_W) << APPROX_W;

		if (OUT !== exp) begin
			$display("\n===== FAILED: A=%0d B=%0d | OUT=%0d EXPECT=%0d =====",
			          a, b, $signed(OUT), exp);
		end
		else begin
			$display("\n===== PASSED: A=%0d B=%0d | OUT=%0d EXPECT=%0d=====",
			          a, b, $signed(OUT), exp);
		end
	end
	endtask

	initial begin
		$dumpfile("tb_multiplier_booth.vcd");
		$dumpvars(0, tb_multiplier_booth);

		clk   = 0;
		rst_n = 0;
		pip_en = 0;
		A = 0;
		B = 0;

		repeat (3) @(posedge clk);
		rst_n = 1;

		repeat (2) @(posedge clk);

		run_test(3, 5);
		run_test(7, 9);
		run_test(12, 4);
		run_test(15, 15);

		if (SIGNED) begin
			run_test(-3, 7);
			run_test(-8, -4);
			run_test(6, -5);
		end

		repeat (10) begin
			run_test($urandom_range(0, 100),
			         $urandom_range(0, 100));
		end

		#20;
		$finish;
	end

endmodule

TB/Multiplier_tb/tb_multiplier_booth.vcd
$date
	Mon Mar  9 15:31:24 2026
$end
$version
	QuestaSim Version 2021.2_1
$end
$timescale
	1ns
$end

$scope module tb_multiplier_booth $end
$var parameter 32 ! WIDTH_A $end
$var parameter 32 " WIDTH_B $end
$var parameter 32 # WIDTH_MUL $end
$var parameter 32 $ SIGNED $end
$var parameter 32 % STAGE $end
$var parameter 32 & APPROX_TYPE $end
$var parameter 32 ' APPROX_W $end
$var parameter 32 ( WIDTH $end
$var parameter 32 ) CNT $end
$var parameter 32 * LATENCY $end
$var reg 1 + clk $end
$var reg 1 , rst_n $end
$var reg 1 - pip_en $end
$var reg 16 . A [15:0] $end
$var reg 16 / B [15:0] $end
$var wire 1 0 OUT [31] $end
$var wire 1 1 OUT [30] $end
$var wire 1 2 OUT [29] $end
$var wire 1 3 OUT [28] $end
$var wire 1 4 OUT [27] $end
$var wire 1 5 OUT [26] $end
$var wire 1 6 OUT [25] $end
$var wire 1 7 OUT [24] $end
$var wire 1 8 OUT [23] $end
$var wire 1 9 OUT [22] $end
$var wire 1 : OUT [21] $end
$var wire 1 ; OUT [20] $end
$var wire 1 < OUT [19] $end
$var wire 1 = OUT [18] $end
$var wire 1 > OUT [17] $end
$var wire 1 ? OUT [16] $end
$var wire 1 @ OUT [15] $end
$var wire 1 A OUT [14] $end
$var wire 1 B OUT [13] $end
$var wire 1 C OUT [12] $end
$var wire 1 D OUT [11] $end
$var wire 1 E OUT [10] $end
$var wire 1 F OUT [9] $end
$var wire 1 G OUT [8] $end
$var wire 1 H OUT [7] $end
$var wire 1 I OUT [6] $end
$var wire 1 J OUT [5] $end
$var wire 1 K OUT [4] $end
$var wire 1 L OUT [3] $end
$var wire 1 M OUT [2] $end
$var wire 1 N OUT [1] $end
$var wire 1 O OUT [0] $end

$scope task run_test $end
$var integer 32 P a $end
$var integer 32 Q b $end
$var integer 32 R exp $end
$upscope $end

$scope module dut $end
$var parameter 32 S APPROX_TYPE $end
$var parameter 32 T APPROX_W $end
$var parameter 32 U WIDTH_A $end
$var parameter 32 V WIDTH_B $end
$var parameter 32 W WIDTH_MUL $end
$var parameter 32 X SIGNED $end
$var parameter 32 Y STAGE $end
$var parameter 32 Z WIDTH $end
$var parameter 32 [ cnt $end
$var wire 1 \ clk $end
$var wire 1 ] rst_n $end
$var wire 1 ^ pip_en $end
$var wire 1 _ A [15] $end
$var wire 1 ` A [14] $end
$var wire 1 a A [13] $end
$var wire 1 b A [12] $end
$var wire 1 c A [11] $end
$var wire 1 d A [10] $end
$var wire 1 e A [9] $end
$var wire 1 f A [8] $end
$var wire 1 g A [7] $end
$var wire 1 h A [6] $end
$var wire 1 i A [5] $end
$var wire 1 j A [4] $end
$var wire 1 k A [3] $end
$var wire 1 l A [2] $end
$var wire 1 m A [1] $end
$var wire 1 n A [0] $end
$var wire 1 o B [15] $end
$var wire 1 p B [14] $end
$var wire 1 q B [13] $end
$var wire 1 r B [12] $end
$var wire 1 s B [11] $end
$var wire 1 t B [10] $end
$var wire 1 u B [9] $end
$var wire 1 v B [8] $end
$var wire 1 w B [7] $end
$var wire 1 x B [6] $end
$var wire 1 y B [5] $end
$var wire 1 z B [4] $end
$var wire 1 { B [3] $end
$var wire 1 | B [2] $end
$var wire 1 } B [1] $end
$var wire 1 ~ B [0] $end
$var wire 1 0 OUT [31] $end
$var wire 1 1 OUT [30] $end
$var wire 1 2 OUT [29] $end
$var wire 1 3 OUT [28] $end
$var wire 1 4 OUT [27] $end
$var wire 1 5 OUT [26] $end
$var wire 1 6 OUT [25] $end
$var wire 1 7 OUT [24] $end
$var wire 1 8 OUT [23] $end
$var wire 1 9 OUT [22] $end
$var wire 1 : OUT [21] $end
$var wire 1 ; OUT [20] $end
$var wire 1 < OUT [19] $end
$var wire 1 = OUT [18] $end
$var wire 1 > OUT [17] $end
$var wire 1 ? OUT [16] $end
$var wire 1 @ OUT [15] $end
$var wire 1 A OUT [14] $end
$var wire 1 B OUT [13] $end
$var wire 1 C OUT [12] $end
$var wire 1 D OUT [11] $end
$var wire 1 E OUT [10] $end
$var wire 1 F OUT [9] $end
$var wire 1 G OUT [8] $end
$var wire 1 H OUT [7] $end
$var wire 1 I OUT [6] $end
$var wire 1 J OUT [5] $end
$var wire 1 K OUT [4] $end
$var wire 1 L OUT [3] $end
$var wire 1 M OUT [2] $end
$var wire 1 N OUT [1] $end
$var wire 1 O OUT [0] $end
$var wire 1 !! Q [2] $end
$var wire 1 "! Q [1] $end
$var wire 1 #! Q [0] $end
$var wire 1 $! A_ext [31] $end
$var wire 1 %! A_ext [30] $end
$var wire 1 &! A_ext [29] $end
$var wire 1 '! A_ext [28] $end
$var wire 1 (! A_ext [27] $end
$var wire 1 )! A_ext [26] $end
$var wire 1 *! A_ext [25] $end
$var wire 1 +! A_ext [24] $end
$var wire 1 ,! A_ext [23] $end
$var wire 1 -! A_ext [22] $end
$var wire 1 .! A_ext [21] $end
$var wire 1 /! A_ext [20] $end
$var wire 1 0! A_ext [19] $end
$var wire 1 1! A_ext [18] $end
$var wire 1 2! A_ext [17] $end
$var wire 1 3! A_ext [16] $end
$var wire 1 4! A_ext [15] $end
$var wire 1 5! A_ext [14] $end
$var wire 1 6! A_ext [13] $end
$var wire 1 7! A_ext [12] $end
$var wire 1 8! A_ext [11] $end
$var wire 1 9! A_ext [10] $end
$var wire 1 :! A_ext [9] $end
$var wire 1 ;! A_ext [8] $end
$var wire 1 <! A_ext [7] $end
$var wire 1 =! A_ext [6] $end
$var wire 1 >! A_ext [5] $end
$var wire 1 ?! A_ext [4] $end
$var wire 1 @! A_ext [3] $end
$var wire 1 A! A_ext [2] $end
$var wire 1 B! A_ext [1] $end
$var wire 1 C! A_ext [0] $end
$var wire 1 D! B_ext [18] $end
$var wire 1 E! B_ext [17] $end
$var wire 1 F! B_ext [16] $end
$var wire 1 G! B_ext [15] $end
$var wire 1 H! B_ext [14] $end
$var wire 1 I! B_ext [13] $end
$var wire 1 J! B_ext [12] $end
$var wire 1 K! B_ext [11] $end
$var wire 1 L! B_ext [10] $end
$var wire 1 M! B_ext [9] $end
$var wire 1 N! B_ext [8] $end
$var wire 1 O! B_ext [7] $end
$var wire 1 P! B_ext [6] $end
$var wire 1 Q! B_ext [5] $end
$var wire 1 R! B_ext [4] $end
$var wire 1 S! B_ext [3] $end
$var wire 1 T! B_ext [2] $end
$var wire 1 U! B_ext [1] $end
$var wire 1 V! B_ext [0] $end
$var wire 1 W! done $end
$var reg 1 X! done_reg $end
$var reg 32 Y! OUT_final [31:0] $end
$var reg 32 Z! product [31:0] $end
$var reg 6 [! i [5:0] $end
$var integer 32 \! p $end
$upscope $end
$upscope $end
$enddefinitions $end
#0
$dumpvars
0+
0,
0-
b0 .
b0 /
0X!
bx Y!
b0 Z!
b0 [!
b10000 !
b10000 "
b100000 #
b0 $
b0 %
b0 &
b0 '
b10000 (
b1000 )
b1000 *
b0 S
b0 T
b10000 U
b10000 V
b100000 W
b0 X
b0 Y
b10000 Z
b1000 [
b1 \!
b0 P
b0 Q
b0 R
0O
0N
0M
0L
0K
0J
0I
0H
0G
0F
0E
0D
0C
0B
0A
0@
0?
0>
0=
0<
0;
0:
09
08
07
06
05
04
03
02
01
00
0#!
0"!
0!!
0C!
0B!
0A!
0@!
0?!
0>!
0=!
0<!
0;!
0:!
09!
08!
07!
06!
05!
04!
03!
02!
01!
00!
0/!
0.!
0-!
0,!
0+!
0*!
0)!
0(!
0'!
0&!
0%!
0$!
0V!
0U!
0T!
0S!
0R!
0Q!
0P!
0O!
0N!
0M!
0L!
0K!
0J!
0I!
0H!
0G!
0F!
0E!
0D!
0W!
0~
0}
0|
0{
0z
0y
0x
0w
0v
0u
0t
0s
0r
0q
0p
0o
0n
0m
0l
0k
0j
0i
0h
0g
0f
0e
0d
0c
0b
0a
0`
0_
0^
0]
0\
$end
#5
1+
1\
b0 \!
b1 \!
#10
0+
0\
#15
1+
1\
#20
0+
0\
#25
1+
1\
1,
1]
#30
0+
0\
#35
1+
1\
#40
0+
0\
#45
1+
1\
b11 P
b101 Q
b11 .
b101 /
1-
b1111 R
1~
1|
1n
1m
1^
1C!
1B!
1U!
1S!
1"!
#50
0+
0\
#55
1+
1\
b11 Z!
b1 [!
#60
0+
0\
#65
1+
1\
b1111 Z!
b10 [!
0"!
#70
0+
0\
#75
1+
1\
b11 [!
#80
0+
0\
#85
1+
1\
b100 [!
#90
0+
0\
#95
1+
1\
b101 [!
#100
0+
0\
#105
1+
1\
b110 [!
#110
0+
0\
#115
1+
1\
b111 [!
#120
0+
0\
#125
1+
1\
b1000 [!
1X!
1W!
#130
0+
0\
#135
1+
1\
b0 Z!
b0 [!
0X!
1"!
1O
1N
1M
1L
0W!
#136
b111 P
b1001 Q
b111 .
b1001 /
b111111 R
0|
1{
1l
1A!
0S!
1R!
#140
0+
0\
#145
1+
1\
b111 Z!
b1 [!
0"!
1!!
#150
0+
0\
#155
1+
1\
b11111111111111111111111111001111 Z!
b10 [!
1#!
0!!
#160
0+
0\
#165
1+
1\
b111111 Z!
b11 [!
0#!
#170
0+
0\
#175
1+
1\
b100 [!
#180
0+
0\
#185
1+
1\
b101 [!
#190
0+
0\
#195
1+
1\
b110 [!
#200
0+
0\
#205
1+
1\
b111 [!
#210
0+
0\
#215
1+
1\
b1000 [!
1X!
1W!
#220
0+
0\
#225
1+
1\
b0 Z!
b0 [!
0X!
1"!
1K
1J
0W!
#226
b1100 P
b100 Q
b1100 .
b100 /
b110000 R
0~
1|
0{
0n
0m
1k
0C!
0B!
1@!
0U!
1S!
0R!
0"!
#230
0+
0\
#235
1+
1\
b1 [!
1"!
#240
0+
0\
#245
1+
1\
b110000 Z!
b10 [!
0"!
#250
0+
0\
#255
1+
1\
b11 [!
#260
0+
0\
#265
1+
1\
b100 [!
#270
0+
0\
#275
1+
1\
b101 [!
#280
0+
0\
#285
1+
1\
b110 [!
#290
0+
0\
#295
1+
1\
b111 [!
#300
0+
0\
#305
1+
1\
b1000 [!
1X!
1W!
#310
0+
0\
#315
1+
1\
b0 Z!
b0 [!
0X!
0O
0N
0M
0L
0W!
#316
b1111 P
b1111 Q
b1111 .
b1111 /
b11100001 R
1~
1}
1{
1n
1m
1C!
1B!
1U!
1T!
1R!
1"!
1!!
#320
0+
0\
#325
1+
1\
b11111111111111111111111111110001 Z!
b1 [!
1#!
#330
0+
0\
#335
1+
1\
b10 [!
0"!
0!!
#340
0+
0\
#345
1+
1\
b11100001 Z!
b11 [!
0#!
#350
0+
0\
#355
1+
1\
b100 [!
#360
0+
0\
#365
1+
1\
b101 [!
#370
0+
0\
#375
1+
1\
b110 [!
#380
0+
0\
#385
1+
1\
b111 [!
#390
0+
0\
#395
1+
1\
b1000 [!
1X!
1W!
#400
0+
0\
#405
1+
1\
b0 Z!
b0 [!
0X!
1"!
1!!
1O
0K
1I
1H
0W!
#406
b1000011 P
b11011 Q
b1000011 .
b11011 /
b11100010001 R
0|
1z
0l
0k
1h
0A!
0@!
1=!
0S!
1Q!
#410
0+
0\
#415
1+
1\
b11111111111111111111111110111101 Z!
b1 [!
1#!
0"!
#420
0+
0\
#425
1+
1\
b11111111111111111111111010110001 Z!
b10 [!
1"!
0!!
#430
0+
0\
#435
1+
1\
b11100010001 Z!
b11 [!
0#!
0"!
#440
0+
0\
#445
1+
1\
b100 [!
#450
0+
0\
#455
1+
1\
b101 [!
#460
0+
0\
#465
1+
1\
b110 [!
#470
0+
0\
#475
1+
1\
b111 [!
#480
0+
0\
#485
1+
1\
b1000 [!
1X!
1W!
#490
0+
0\
#495
1+
1\
b0 Z!
b0 [!
0X!
1"!
1!!
1K
0J
0I
0H
1G
1F
1E
0W!
#496
b100011 P
b1011101 Q
b100011 .
b1011101 /
b110010110111 R
0}
1|
1x
1i
0h
1>!
0=!
0T!
1S!
1O!
0!!
#500
0+
0\
#505
1+
1\
b100011 Z!
b1 [!
1!!
#510
0+
0\
#515
1+
1\
b11111111111111111111111110010111 Z!
b10 [!
1#!
0!!
#520
0+
0\
#525
1+
1\
b1111110111 Z!
b11 [!
0#!
#530
0+
0\
#535
1+
1\
b110010110111 Z!
b100 [!
0"!
#540
0+
0\
#545
1+
1\
b101 [!
#550
0+
0\
#555
1+
1\
b110 [!
#560
0+
0\
#565
1+
1\
b111 [!
#570
0+
0\
#575
1+
1\
b1000 [!
1X!
1W!
#580
0+
0\
#585
1+
1\
b0 Z!
b0 [!
0X!
1"!
1N
1M
1J
1H
0G
0F
1D
0W!
#586
b1001100 P
b101000 Q
b1001100 .
b101000 /
b101111100000 R
0~
0|
0z
1y
0x
0n
0m
1l
1k
0i
1h
0C!
0B!
1A!
1@!
0>!
1=!
0U!
0S!
0Q!
1P!
0O!
0"!
#590
0+
0\
#595
1+
1\
b1 [!
1!!
#600
0+
0\
#605
1+
1\
b11111111111111111111110110100000 Z!
b10 [!
1#!
#610
0+
0\
#615
1+
1\
b11111111111111111111100011100000 Z!
b11 [!
0!!
#620
0+
0\
#625
1+
1\
b101111100000 Z!
b100 [!
0#!
#630
0+
0\
#635
1+
1\
b101 [!
#640
0+
0\
#645
1+
1\
b110 [!
#650
0+
0\
#655
1+
1\
b111 [!
#660
0+
0\
#665
1+
1\
b1000 [!
1X!
1W!
#670
0+
0\
#675
1+
1\
b0 Z!
b0 [!
0X!
0O
0N
0M
0K
1I
1G
1F
0E
0W!
#676
b111111 P
b110010 Q
b111111 .
b110010 /
b110001001110 R
1}
0{
1z
1n
1m
1j
1i
0h
1C!
1B!
1?!
1>!
0=!
1T!
0R!
1Q!
1!!
#680
0+
0\
#685
1+
1\
b11111111111111111111111110000010 Z!
b1 [!
1#!
0!!
#690
0+
0\
#695
1+
1\
b1111110 Z!
b10 [!
0#!
1"!
1!!
#700
0+
0\
#705
1+
1\
b11111111111111111111110010001110 Z!
b11 [!
1#!
0"!
0!!
#710
0+
0\
#715
1+
1\
b110001001110 Z!
b100 [!
0#!
#720
0+
0\
#725
1+
1\
b101 [!
#730
0+
0\
#735
1+
1\
b110 [!
#740
0+
0\
#745
1+
1\
b111 [!
#750
0+
0\
#755
1+
1\
b1000 [!
1X!
1W!
#760
0+
0\
#765
1+
1\
b0 Z!
b0 [!
0X!
1!!
1N
1M
1L
0J
0H
0G
0F
1E
0W!
#766
b1011100 P
b111110 Q
b1011100 .
b111110 /
b1011001001000 R
1|
1{
0n
0m
0i
1h
0C!
0B!
0>!
1=!
1S!
1R!
#770
0+
0\
#775
1+
1\
b11111111111111111111111101001000 Z!
b1 [!
1#!
1"!
#780
0+
0\
#785
1+
1\
b10 [!
#790
0+
0\
#795
1+
1\
b11 [!
0"!
0!!
#800
0+
0\
#805
1+
1\
b1011001001000 Z!
b100 [!
0#!
#810
0+
0\
#815
1+
1\
b101 [!
#820
0+
0\
#825
1+
1\
b110 [!
#830
0+
0\
#835
1+
1\
b111 [!
#840
0+
0\
#845
1+
1\
b1000 [!
1X!
1W!
#850
0+
0\
#855
1+
1\
b0 Z!
b0 [!
0X!
1!!
0N
0M
1F
0D
1C
0W!
#856
b111000 P
b100 Q
b111000 .
b100 /
b11100000 R
0}
0{
0z
0y
0l
1i
0h
0A!
1>!
0=!
0T!
0R!
0Q!
0P!
0!!
#860
0+
0\
#865
1+
1\
b1 [!
1"!
#870
0+
0\
#875
1+
1\
b11100000 Z!
b10 [!
0"!
#880
0+
0\
#885
1+
1\
b11 [!
#890
0+
0\
#895
1+
1\
b100 [!
#900
0+
0\
#905
1+
1\
b101 [!
#910
0+
0\
#915
1+
1\
b110 [!
#920
0+
0\
#925
1+
1\
b111 [!
#930
0+
0\
#935
1+
1\
b1000 [!
1X!
1W!
#940
0+
0\
#945
1+
1\
b0 Z!
b0 [!
0X!
0L
1J
1H
0F
0E
0C
0W!
#946
b1011101 P
b111111 Q
b1011101 .
b111111 /
b1011011100011 R
1~
1}
1{
1z
1y
1n
1l
0i
1h
1C!
1A!
0>!
1=!
1U!
1T!
1R!
1Q!
1P!
1"!
1!!
#950
0+
0\
#955
1+
1\
b11111111111111111111111110100011 Z!
b1 [!
1#!
#960
0+
0\
#965
1+
1\
b10 [!
#970
0+
0\
#975
1+
1\
b11 [!
0"!
0!!
#980
0+
0\
#985
1+
1\
b1011011100011 Z!
b100 [!
0#!
#990
0+
0\
#995
1+
1\
b101 [!
#1000
0+
0\
#1005
1+
1\
b110 [!
#1010
0+
0\
#1015
1+
1\
b111 [!
#1020
0+
0\
#1025
1+
1\
b1000 [!
1X!
1W!
#1030
0+
0\
#1035
1+
1\
b0 Z!
b0 [!
0X!
1"!
1!!
1O
1N
1F
1E
1C
0W!
#1036
b11001 P
b101100 Q
b11001 .
b101100 /
b10001001100 R
0~
0}
0z
0l
0h
0A!
0=!
0U!
0T!
0Q!
0"!
0!!
#1040
0+
0\
#1045
1+
1\
b1 [!
1"!
1!!
#1050
0+
0\
#1055
1+
1\
b11111111111111111111111110011100 Z!
b10 [!
1#!
0"!
#1060
0+
0\
#1065
1+
1\
b11111111111111111111111000001100 Z!
b11 [!
0!!
#1070
0+
0\
#1075
1+
1\
b10001001100 Z!
b100 [!
0#!
#1080
0+
0\
#1085
1+
1\
b101 [!
#1090
0+
0\
#1095
1+
1\
b110 [!
#1100
0+
0\
#1105
1+
1\
b111 [!
#1110
0+
0\
#1115
1+
1\
b1000 [!
1X!
1W!
#1120
0+
0\
#1125
1+
1\
b0 Z!
b0 [!
0X!
0O
0N
1M
1L
0J
0H
0F
0C
0W!
#1126
b1010100 P
b1010100 .
b111001110000 R
0n
1l
0k
1h
0C!
1A!
0@!
1=!
#1130
0+
0\
#1135
1+
1\
b1 [!
1"!
1!!
#1140
0+
0\
#1145
1+
1\
b11111111111111111111111010110000 Z!
b10 [!
1#!
0"!
#1150
0+
0\
#1155
1+
1\
b11111111111111111111100101110000 Z!
b11 [!
0!!
#1160
0+
0\
#1165
1+
1\
b111001110000 Z!
b100 [!
0#!
#1170
0+
0\
#1175
1+
1\
b101 [!
#1180
0+
0\
#1185
1+
1\
b110 [!
#1190
0+
0\
#1195
1+
1\
b111 [!
#1200
0+
0\
#1205
1+
1\
b1000 [!
1X!
1W!
#1210
0+
0\
#1215
1+
1\
b0 Z!
b0 [!
0X!
0M
0L
1K
1J
1F
1D
0W!
#1216
b1110 P
b111010 Q
b1110 .
b111010 /
b1100101100 R
1}
0|
1z
1m
1k
0j
0h
1B!
1@!
0?!
0=!
1T!
0S!
1Q!
1!!
#1220
0+
0\
#1225
1+
1\
b11111111111111111111111111100100 Z!
b1 [!
1#!
#1230
0+
0\
#1235
1+
1\
b11111111111111111111111110101100 Z!
b10 [!
1"!
#1240
0+
0\
#1245
1+
1\
b11 [!
0"!
0!!
#1250
0+
0\
#1255
1+
1\
b1100101100 Z!
b100 [!
0#!
#1260
0+
0\
#1265
1+
1\
b101 [!
#1270
0+
0\
#1275
1+
1\
b110 [!
#1280
0+
0\
#1285
1+
1\
b111 [!
#1290
0+
0\
#1295
1+
1\
b1000 [!
1X!
1W!
#1300
0+
0\
#1305
1+
1\
b0 Z!
b0 [!
0X!
1!!
1M
1L
0K
0I
1G
0E
0D
0W!
#1310
0+
0\
#1315
1+
1\
b11111111111111111111111111100100 Z!
b1 [!
1#!
#1320
0+
0\
#1325
1+
1\
b11111111111111111111111110101100 Z!
b10 [!
1"!
