RTL/systolic_array/Multiplier/Multiplier_2x2.v
module Multiplier_2x2 #(
	parameter	APPROX = 0
)(
	input	wire	[1:0]	A,
	input	wire	[1:0]	B,

	output	reg	[3:0]	OUT
);

	wire	AND_10, AND_01, AND_11, AND_10_01;
	
	assign	AND_10		= A[1] & B[0];	
	assign	AND_01		= A[0] & B[1];	
	assign	AND_11		= A[1] & B[1];
	assign	AND_10_01	= AND_10 & AND_01;	
	
	always @(*) begin
		if(APPROX) begin
			OUT[0]	= A[0] & B[0];
	 		OUT[1]	= AND_10 | AND_01;
	 		OUT[2]	= AND_11;
			OUT[3]	= 1'b0;
		end 
		else begin
			OUT[0]	= A[0] & B[0];
	 		OUT[1]	= AND_10 ^ AND_01;
	 		OUT[2]	= AND_10_01 ^ AND_11;
			OUT[3]	= AND_10_01 & AND_11;
		end
	end

endmodule

TB/Multiplier_tb/tb_Multiplier_2x2.sv
module tb_Multiplier_2x2;

    logic [1:0] A, B;
    logic [3:0] OUT_exact;
    logic [3:0] OUT_approx;

    logic [3:0] GOLD;

    Multiplier_2x2 #(.APPROX(0)) dut_exact (
        .A(A),
        .B(B),
        .OUT(OUT_exact)
    );

    Multiplier_2x2 #(.APPROX(1)) dut_approx (
        .A(A),
        .B(B),
        .OUT(OUT_approx)
    );

    initial begin
        $dumpfile("tb_Multiplier_2x2.vcd");
        $dumpvars(0, tb_Multiplier_2x2);

        $display(" A  B | GOLD | EXACT | APPROX");

        for (int i = 0; i < 4; i++) begin
            for (int j = 0; j < 4; j++) begin
                A = i[1:0];
                B = j[1:0];
                #1;

                GOLD = i * j;

                $display("%8b %8b |  %b  |   %b  |   %b",
                         i, j, GOLD, OUT_exact, OUT_approx);

                if (OUT_exact !== GOLD) begin
                  	$display("FAIL!!");
                    	$stop;
                end
            end
        end

      $display("PASSED SUCCESSFULLY!!");
      $finish;
    end

endmodule

TB/Multiplier_tb/tb_Multiplier_2x2.vcd
$date
	Mon Mar  9 15:11:31 2026
$end
$version
	QuestaSim Version 2021.2_1
$end
$timescale
	1ns
$end

$scope module tb_Multiplier_2x2 $end
$var reg 2 ! A [1:0] $end
$var reg 2 " B [1:0] $end
$var reg 4 # OUT_exact [3:0] $end
$var reg 4 $ OUT_approx [3:0] $end
$var reg 4 % GOLD [3:0] $end

$scope module dut_exact $end
$var parameter 32 & APPROX $end
$var wire 1 ' A [1] $end
$var wire 1 ( A [0] $end
$var wire 1 ) B [1] $end
$var wire 1 * B [0] $end
$var reg 4 + OUT [3:0] $end
$var wire 1 , AND_10 $end
$var wire 1 - AND_01 $end
$var wire 1 . AND_11 $end
$var wire 1 / AND_10_01 $end
$upscope $end

$scope module dut_approx $end
$var parameter 32 0 APPROX $end
$var wire 1 1 A [1] $end
$var wire 1 2 A [0] $end
$var wire 1 3 B [1] $end
$var wire 1 4 B [0] $end
$var reg 4 5 OUT [3:0] $end
$var wire 1 6 AND_10 $end
$var wire 1 7 AND_01 $end
$var wire 1 8 AND_11 $end
$var wire 1 9 AND_10_01 $end
$upscope $end
$upscope $end
$enddefinitions $end
#0
$dumpvars
b0 !
b0 "
b0 #
b0 $
bx %
b0 +
b0 5
b0 &
b1 0
0,
0-
0.
0/
06
07
08
09
04
03
02
01
0*
0)
0(
0'
$end
#1
b0 %
b1 "
14
1*
#2
b10 "
04
13
0*
1)
#3
b11 "
14
1*
#4
b1 !
b0 "
04
03
0*
0)
12
1(
#5
b1 "
14
1*
b1 +
b1 5
b1 $
b1 #
#6
b1 %
b10 "
04
13
0*
1)
17
1-
b0 +
b10 +
b0 5
b10 5
b10 $
b10 #
#7
b10 %
b11 "
14
1*
b11 +
b11 5
b11 $
b11 #
#8
b11 %
b10 !
b0 "
04
03
0*
0)
02
11
0(
1'
07
0-
b10 +
b0 +
b10 5
b0 5
b0 $
b0 #
#9
b0 %
b1 "
14
1*
16
1,
b10 +
b10 5
b10 $
b10 #
#10
b10 %
b10 "
04
13
0*
1)
06
18
0,
1.
b0 +
b100 +
b0 5
b100 5
b100 $
b100 #
#11
b100 %
b11 "
14
1*
16
1,
b110 +
b110 5
b110 $
b110 #
#12
b110 %
b11 !
b0 "
04
03
0*
0)
12
1(
06
08
0,
0.
b100 +
b0 +
b100 5
b0 5
b0 $
b0 #
#13
b0 %
b1 "
14
1*
16
1,
b1 +
b11 +
b1 5
b11 5
b11 $
b11 #
#14
b11 %
b10 "
04
13
0*
1)
06
18
17
0,
1.
1-
b10 +
b110 +
b10 5
b110 5
b110 $
b110 #
#15
b110 %
b11 "
14
1*
16
1,
19
1/
b111 +
b101 +
b1 +
b1001 +
b111 5
b111 $
b1001 #
#16
b1001 %
