RTL/systolic_array/Adder/Adder_gear.v
//Return max number between 2 numbers
`define max(a,b) ((a) > (b) ? (a) : (b))

module Adder_gear #(
	parameter 	R = 16,					//number of shifted bit
	parameter 	P = 16,					//overlap bit
	parameter 	WIDTH_A = 16,			//Width of A
	parameter 	WIDTH_B = 16			//Width of B
)(
	input	wire	[WIDTH_A-1:0]					A,
	input	wire	[WIDTH_B-1:0]					B,
	input	wire									Carry,	//do not use Carry

	output	wire	[`max(WIDTH_A, WIDTH_B)-1:0]	OUT		//Width of output is max between Width of A and B
);
	//Derived Parameters
	parameter 			BITS 	= `max(WIDTH_A, WIDTH_B);				//operands width
	parameter 			L 		= R + P;								//sub-adder length
	parameter 	integer k 		= 1 + ((BITS - L + R - 1) / R);			//number of loops
	parameter 			N		= L + (k-1)*R;							//real width of sum

	//Internal Signals
	wire	signed	[N-1:0]			Sum;
	wire	signed	[BITS-1:0] 		a;
	wire	signed	[BITS-1:0] 		b;
	wire	signed	[L-1:0]			subadd_A [k-1:0]; 
	wire	signed	[L-1:0]			subadd_B [k-1:0]; 
	wire	signed	[N:0]			subadd_sum [k-1:0];
	wire 			[k:0] 			carry;

	//Sub Adder local carry
	assign 	carry[0] = 1'b0;

	//Sign extend
	assign	a = {{{BITS-WIDTH_A}{A[WIDTH_A-1]}}, A};	
	assign	b = {{{BITS-WIDTH_B}{B[WIDTH_B-1]}}, B};	

	//Create loop to sum Sub Adder
	genvar i;
	generate
		for(i=0; i<k; i=i+1) begin
			//Create Sub-Adder
			assign subadd_A[i] = a[i*R+:L];
			assign subadd_B[i] = b[i*R+:L];

			//Sum the sub-adders
			assign subadd_sum[i] = subadd_A[i] + subadd_B[i] + carry[i];
			//Create carry for next block
			assign carry[i+1] 		= subadd_sum[i][L];

			//First block
			if(i==0) begin
				assign Sum[L-1:0] = subadd_sum[0][L-1:0];
			end
			else begin
				//Each loop contributes R bits
				//L = R + P bits
				assign Sum[P + i*R +:R] = subadd_sum[i][L-1:P];
			end
		end
	endgenerate

	assign OUT = Sum;
endmodule

TB/Adder_tb/tb_adder_gear.sv
module tb_adder_gear;

	localparam int R 		= 4;
	localparam int P 		= 4;
	localparam int WIDTH_A 	= 8;
	localparam int WIDTH_B 	= 12;
	localparam int BITS    	= (WIDTH_A > WIDTH_B) ? WIDTH_A : WIDTH_B;

	logic	[WIDTH_A-1:0] 	A;
	logic	[WIDTH_B-1:0]	B;
	logic 					Carry;
	
	logic 	[BITS-1:0]		OUT;

	Adder_gear #(
		.R(R),
		.P(P),
		.WIDTH_A(WIDTH_A),
		.WIDTH_B(WIDTH_B)
	) dut(
		.A(A),
		.B(B),
		.Carry(Carry),
		.OUT(OUT)		
	);

	task automatic display_result();
		$display(
			"A=%0d, B=%0d, Carry=%b, OUT=%0d", $signed(A), $signed(B), Carry, $signed(OUT)
		);
		$display(
			"A=%b, B=%b, Carry=%b, OUT=%b", $signed(A), $signed(B), Carry, OUT
		);
	endtask

	initial begin
		$dumpfile("tb_adder_gear.vcd");   
       	$dumpvars(0, tb_adder_gear);   
		A = 8'sd5;
		B = 12'sd3;
		Carry = 0;
		#1 display_result();

		A = -8'sd5;
        B = 12'sd3;
        Carry = 0;
        #1 display_result();

        A = -8'sd5;
        B = -12'sd7;
        Carry = 0;
        #1 display_result();

        A = -8'sd1;
        B = 12'sd1;
        Carry = 0;
        #1 display_result();

        A = -8'sd1;
        B = 12'sd1;
        Carry = 1;
        #1 display_result();

        A = 8'sd127;
        B = 12'sd1;
        Carry = 0;
        #1 display_result();

        A = -8'sd128;
        B = -12'sd1;
        Carry = 0;
        #1 display_result();

		A = -8'sd5;
        B = 12'sd5;
        Carry = 0;
        #1 display_result();

        A = -8'sd5;
        B = -12'sd5;
        Carry = 0;
        #1 display_result();

        A = -8'sd2;
        B = 12'sd1;
        Carry = 0;
        #1 display_result();

        A = -8'sd1;
        B = 12'sd0;
        Carry = 1;
        #1 display_result();

        A = 8'sd42;
        B = 12'sd45;
        Carry = 0;
        #1 display_result();

        A = -8'sd128;
        B = 12'sd128;
        Carry = 0;
        #1 display_result();

       	#1 $finish;
	end	

endmodule

Adder_tb/tb_adder_gear.vcd
$date
	Tue Mar  3 11:10:10 2026
$end
$version
	QuestaSim Version 2021.2_1
$end
$timescale
	1ns
$end

$scope module tb_adder_gear $end
$var reg 12 ! OUT [11:0] $end

$scope task display_result $end
$upscope $end

$scope module dut $end
$upscope $end
$upscope $end
$enddefinitions $end
#0
$dumpvars
b1000 !
$end
#1
b111100001000 !
b111111111110 !
#2
b111111110100 !
#3
b0 !
#5
b10000000 !
#6
b111101111111 !
#7
b0 !
#8
b111111110110 !
#9
b111111111111 !
#11
b1010111 !
#12
b0 !
